[
  {
    "at": "00:01:04.531",
    "scene-type": "S",
    "scene-subtype": "D",
    "transitional": false,
    "text-transcript": "STATELINE: LEG. REP.\nPROGRAM NO.: 1505\nTAPE DATE: 06/21/88\nAIR DATE: 06/21/88 19:30 LIVE!\nREPEAT: 06/22/88    7:00\nTAPE NO.: TH 4850\nLENGTH: 28:45\nDIRECTOR: SHEEHAN",
    "keyed-information": {
      "series-title": "Stateline: Leg. Rep.",
      "episode-no": "1505",
      "create-date": "1988-06-21",
      "air-date": "1988-06-22",
      "director": "Sheehan"
    }
  }
]