[
  {
    "at": "00:03:22.535",
    "scene-type": "S",
    "scene-subtype": "D",
    "transitional": false,
    "text-transcript": "On the Same Page\nPanel Discussion\nDonna Tartt\nDt:   1-21-03\nHost: Tommy Sanders\nPanelists: Mulkey, Brazzel,\n           Webb\nProducer: Sanders\nDirector: Worden",
    "keyed-information": {
      "series-title": " On the Same Page ",
      "episode-title": " Panel Discussion Donna Tartt",
      "date": " 2003-01-21",
      "director": " Worden",
      "producer": " Sanders"
    }
  }
]