[
  {
    "at": "00:01:38.631",
    "scene-lebal": "I",
    "scene-subtype-label": "",
    "transitional": false,
    "text-transcript": "DAN BOYLAN\n\nNewsmakers",
    "keyed-information": {
      "name-as-written": "DAN BOYLAN",
      "name-normalized": "Boylan, Dan",
      "attributes": [
        "Newsmakers"
      ]
    }
  },
  {
    "at": "00:02:57.644",
    "scene-lebal": "I",
    "scene-subtype-label": "",
    "transitional": false,
    "text-transcript": "RANDALL KUSAKA (D)\n\nState Rep. Dist. 33 Candidate\n\nRed Hill, Halawa Heights, Pearlridge, Aiea",
    "keyed-information": {
      "name-as-written": "RANDALL KUSAKA (D)",
      "name-normalized": "Kusaka, Randall",
      "attributes": [
        "State Rep. Dist. 33 Candidate",
        "Red Hill, Halawa Heights, Pearlridge, Aiea"
      ]
    }
  },
  {
    "at": "00:03:16.129",
    "scene-lebal": "I",
    "scene-subtype-label": "",
    "transitional": false,
    "text-transcript": "BLAKE OSHIRO (D)\n\nState Rep. Dist. 33 Candidate\n\nRed Hill, Halawa Heights, Pearlridge, Aiea",
    "keyed-information": {
      "name-as-written": "BLAKE OSHIRO (D)",
      "name-normalized": "Oshiro, Blake",
      "attributes": [
        "State Rep. Dist. 33 Candidate",
        "Red Hill, Halawa Heights, Pearlridge, Aiea"
      ]
    }
  },
  {
    "at": "00:07:32.885",
    "scene-lebal": "I",
    "scene-subtype-label": "",
    "transitional": false,
    "text-transcript": "RANDALL KUSAKA (D)\n\nState Rep. Dist. 33 Candidate\n\nRed Hill, Halawa Heights, Pearlridge, Aiea",
    "keyed-information": {
      "name-as-written": "RANDALL KUSAKA (D)",
      "name-normalized": "Kusaka, Randall",
      "attributes": [
        "State Rep. Dist. 33 Candidate",
        "Red Hill, Halawa Heights, Pearlridge, Aiea"
      ]
    }
  },
  {
    "at": "00:08:29.509",
    "scene-lebal": "I",
    "scene-subtype-label": "",
    "transitional": false,
    "text-transcript": "BLAKE OSHIRO (D)\n\nState Rep. Dist. 33 Candidate\n\nRed Hill, Halawa Heights, Pearlridge, Aiea",
    "keyed-information": {
      "name-as-written": "BLAKE OSHIRO (D)",
      "name-normalized": "Oshiro, Blake",
      "attributes": [
        "State Rep. Dist. 33 Candidate",
        "Red Hill, Halawa Heights, Pearlridge, Aiea"
      ]
    }
  },
  {
    "at": "00:12:54.406",
    "scene-lebal": "I",
    "scene-subtype-label": "",
    "transitional": false,
    "text-transcript": "RANDALL KUSAKA (D)\n\nState Rep. Dist. 33 Candidate\n\nRed Hill, Halawa Heights, Pearlridge, Aiea",
    "keyed-information": {
      "name-as-written": "RANDALL KUSAKA (D)",
      "name-normalized": "Kusaka, Randall",
      "attributes": [
        "State Rep. Dist. 33 Candidate",
        "Red Hill, Halawa Heights, Pearlridge, Aiea"
      ]
    }
  },
  {
    "at": "00:16:01.760",
    "scene-lebal": "I",
    "scene-subtype-label": "",
    "transitional": false,
    "text-transcript": "EVE ANDERSON (R)\n\nState Rep. Dist. 51 Candidate\n\nWaimanalo, Keola Hills, Lanikai, Kailua, Enchanted Lake",
    "keyed-information": {
      "name-as-written": "EVE ANDERSON (R)",
      "name-normalized": "Anderson, Eve",
      "attributes": [
        "State Rep. Dist. 51 Candidate",
        "Waimanalo, Keola Hills, Lanikai, Kailua, Enchanted Lake"
      ]
    }
  },
  {
    "at": "00:17:08.260",
    "scene-lebal": "I",
    "scene-subtype-label": "",
    "transitional": false,
    "text-transcript": "JOE GOMES (R)\n\nState Rep. Dist. 51 Candidate\n\nWaimanalo, Keola Hills, Lanikai, Kailua, Enchanted Lake",
    "keyed-information": {
      "name-as-written": "JOE GOMES (R)",
      "name-normalized": "Gomes, Joe",
      "attributes": [
        "State Rep. Dist. 51 Candidate",
        "Waimanalo, Keola Hills, Lanikai, Kailua, Enchanted Lake"
      ]
    }
  },
  {
    "at": "00:20:15.013",
    "scene-lebal": "I",
    "scene-subtype-label": "",
    "transitional": false,
    "text-transcript": "EVE ANDERSON (R)\n\nState Rep. Dist. 51 Candidate\n\nWaimanalo, Keola Hills, Lanikai, Kailua, Enchanted Lake",
    "keyed-information": {
      "name-as-written": "EVE ANDERSON (R)",
      "name-normalized": "Anderson, Eve",
      "attributes": [
        "State Rep. Dist. 51 Candidate",
        "Waimanalo, Keola Hills, Lanikai, Kailua, Enchanted Lake"
      ]
    }
  },
  {
    "at": "00:25:48.780",
    "scene-lebal": "I",
    "scene-subtype-label": "",
    "transitional": false,
    "text-transcript": "JOE GOMES (R)\n\nState Rep. Dist. 51 Candidate\n\nWaimanalo, Keola Hills, Lanikai, Kailua, Enchanted Lake",
    "keyed-information": {
      "name-as-written": "JOE GOMES (R)",
      "name-normalized": "Gomes, Joe",
      "attributes": [
        "State Rep. Dist. 51 Candidate",
        "Waimanalo, Keola Hills, Lanikai, Kailua, Enchanted Lake"
      ]
    }
  },
  {
    "at": "00:27:13.632",
    "scene-lebal": "I",
    "scene-subtype-label": "",
    "transitional": false,
    "text-transcript": "EVE ANDERSON (R)\n\nState Rep. Dist. 51 Candidate\n\nWaimanalo, Keola Hills, Lanikai, Kailua, Enchanted Lake",
    "keyed-information": {
      "name-as-written": "EVE ANDERSON (R)",
      "name-normalized": "Anderson, Eve",
      "attributes": [
        "State Rep. Dist. 51 Candidate",
        "Waimanalo, Keola Hills, Lanikai, Kailua, Enchanted Lake"
      ]
    }
  }
]