[
  {
    "at": "00:04:40.380",
    "scene-lebal": "I",
    "scene-subtype-label": "",
    "transitional": false,
    "text-transcript": "NORMAN SANDLER\n\nUNITED PRESS INTERNATIONAL",
    "keyed-information": {
      "name-as-written": "NORMAN SANDLER",
      "name-normalized": "Sandler, Norman ",
      "attributes": [
        "UNITED PRESS INTERNATIONAL"
      ]
    }
  },
  {
    "at": "00:05:33.266",
    "scene-lebal": "I",
    "scene-subtype-label": "",
    "transitional": false,
    "text-transcript": "GEORGE BUSH\n\n(R) TEXAS",
    "keyed-information": {
      "name-as-written": "GEORGE BUSH",
      "name-normalized": "Bush, George",
      "attributes": [
        "(R) TEXAS"
      ]
    }
  },
  {
    "at": "00:06:38.030",
    "scene-lebal": "I",
    "scene-subtype-label": "",
    "transitional": false,
    "text-transcript": "DANIEL PEDERSEN\n\nDES MOINES REGISTER",
    "keyed-information": {
      "name-as-written": "DANIEL PEDERSEN",
      "name-normalized": "Pedersen, Daniel",
      "attributes": [
        "DES MOINES REGISTER"
      ]
    }
  },
  {
    "at": "00:07:23.276",
    "scene-lebal": "I",
    "scene-subtype-label": "",
    "transitional": false,
    "text-transcript": "JOHN McCORMALY",
    "keyed-information": {
      "name-as-written": "JOHN McCORMALY",
      "name-normalized": "McCormaly, John",
      "attributes": []
    }
  },
  {
    "at": "00:08:27.406",
    "scene-lebal": "I",
    "scene-subtype-label": "",
    "transitional": false,
    "text-transcript": "GEORGE BUSH\n\n(R) TEXAS",
    "keyed-information": {
      "name-as-written": "GEORGE BUSH",
      "name-normalized": "Bush, George",
      "attributes": [
        "(R) TEXAS"
      ]
    }
  },
  {
    "at": "00:09:36.876",
    "scene-lebal": "I",
    "scene-subtype-label": "",
    "transitional": false,
    "text-transcript": "GEORGE BUSH\n\n(R) TEXAS",
    "keyed-information": {
      "name-as-written": "GEORGE BUSH",
      "name-normalized": "Bush, George",
      "attributes": [
        "(R) TEXAS"
      ]
    }
  },
  {
    "at": "00:12:27.012",
    "scene-lebal": "I",
    "scene-subtype-label": "",
    "transitional": false,
    "text-transcript": "GEORGE BUSH\n\n(R) TEXAS",
    "keyed-information": {
      "name-as-written": "GEORGE BUSH",
      "name-normalized": "Bush, George",
      "attributes": [
        "(R) TEXAS"
      ]
    }
  },
  {
    "at": "00:12:42.895",
    "scene-lebal": "I",
    "scene-subtype-label": "",
    "transitional": false,
    "text-transcript": "JOHN McCORMALY",
    "keyed-information": {
      "name-as-written": "JOHN McCORMALY",
      "name-normalized": "McCormaly, John",
      "attributes": []
    }
  },
  {
    "at": "00:16:40.499",
    "scene-lebal": "I",
    "scene-subtype-label": "",
    "transitional": false,
    "text-transcript": "GEORGE BUSH\n\n(R) TEXAS",
    "keyed-information": {
      "name-as-written": "GEORGE BUSH",
      "name-normalized": "Bush, George",
      "attributes": [
        "(R) TEXAS"
      ]
    }
  },
  {
    "at": "00:17:32.017",
    "scene-lebal": "I",
    "scene-subtype-label": "",
    "transitional": false,
    "text-transcript": "DANIEL PEDERSEN\n\nDES MOINES REGISTER",
    "keyed-information": {
      "name-as-written": "DANIEL PEDERSEN",
      "name-normalized": "Pedersen, Daniel",
      "attributes": [
        "DES MOINES REGISTER"
      ]
    }
  },
  {
    "at": "00:21:45.771",
    "scene-lebal": "I",
    "scene-subtype-label": "",
    "transitional": false,
    "text-transcript": "GEORGE BUSH\n\n(R) TEXAS",
    "keyed-information": {
      "name-as-written": "GEORGE BUSH",
      "name-normalized": "Bush, George",
      "attributes": [
        "(R) TEXAS"
      ]
    }
  },
  {
    "at": "00:24:32.137",
    "scene-lebal": "I",
    "scene-subtype-label": "",
    "transitional": false,
    "text-transcript": "NORMAN SANDLER\n\nUNITED PRESS INTERNATIONAL",
    "keyed-information": {
      "name-as-written": "NORMAN SANDLER",
      "name-normalized": "Sandler, Norman",
      "attributes": [
        "UNITED PRESS INTERNATIONAL"
      ]
    }
  },
  {
    "at": "00:24:53.258",
    "scene-lebal": "I",
    "scene-subtype-label": "",
    "transitional": false,
    "text-transcript": "GEORGE BUSH\n\n(R) TEXAS",
    "keyed-information": {
      "name-as-written": "GEORGE BUSH",
      "name-normalized": "Bush, George",
      "attributes": [
        "(R) TEXAS"
      ]
    }
  },
  {
    "at": "00:33:32.010",
    "scene-lebal": "I",
    "scene-subtype-label": "",
    "transitional": false,
    "text-transcript": "HOWARD BAKER\n\nTENNESSEE",
    "keyed-information": {
      "name-as-written": "HOWARD BAKER",
      "name-normalized": "Baker, Howard",
      "attributes": [
        "TENNESSEE"
      ]
    }
  },
  {
    "at": "00:35:24.388",
    "scene-lebal": "I",
    "scene-subtype-label": "",
    "transitional": false,
    "text-transcript": "HOWARD BAKER\n\n(R) TENNESSEE",
    "keyed-information": {
      "name-as-written": "HOWARD BAKER",
      "name-normalized": "Baker, Howard",
      "attributes": [
        "(R) TENNESSEE"
      ]
    }
  },
  {
    "at": "00:35:44.876",
    "scene-lebal": "I",
    "scene-subtype-label": "",
    "transitional": false,
    "text-transcript": "JOHN McCORMALLY\n\nHARRIS NEWSPAPERS",
    "keyed-information": {
      "name-as-written": "JOHN McCORMALLY",
      "name-normalized": "McCormally, John",
      "attributes": [
        "HARRIS NEWSPAPERS"
      ]
    }
  },
  {
    "at": "00:37:16.634",
    "scene-lebal": "I",
    "scene-subtype-label": "",
    "transitional": false,
    "text-transcript": "DAVID YEPSEN\n\nDES MOINES REGISTER",
    "keyed-information": {
      "name-as-written": "DAVID YEPSEN",
      "name-normalized": "Yepsen, David",
      "attributes": [
        "DES MOINES REGISTER"
      ]
    }
  },
  {
    "at": "00:40:56.020",
    "scene-lebal": "I",
    "scene-subtype-label": "",
    "transitional": false,
    "text-transcript": "HOWARD BAKER\n\n(R) TENNESSEE",
    "keyed-information": {
      "name-as-written": "HOWARD BAKER",
      "name-normalized": "Baker, Howard",
      "attributes": [
        "(R) TENNESSEE"
      ]
    }
  },
  {
    "at": "00:43:46.023",
    "scene-lebal": "I",
    "scene-subtype-label": "",
    "transitional": false,
    "text-transcript": "NORMAN SANDLER\n\nUNITED PRESS INTERNATIONAL",
    "keyed-information": {
      "name-as-written": "NORMAN SANDLER",
      "name-normalized": "Sandler, Norman",
      "attributes": [
        "UNITED PRESS INTERNATIONAL"
      ]
    }
  },
  {
    "at": "00:45:04.768",
    "scene-lebal": "I",
    "scene-subtype-label": "",
    "transitional": false,
    "text-transcript": "DAVID YEPSEN\n\nDES MOINES REGISTER",
    "keyed-information": {
      "name-as-written": "DAVID YEPSEN",
      "name-normalized": "Yepsen, David",
      "attributes": [
        "DES MOINES REGISTER"
      ]
    }
  },
  {
    "at": "00:46:40.764",
    "scene-lebal": "I",
    "scene-subtype-label": "",
    "transitional": false,
    "text-transcript": "HOWARD BAKER\n\n(R) TENNESSEE",
    "keyed-information": {
      "name-as-written": "HOWARD BAKER",
      "name-normalized": "Baker, Howard",
      "attributes": [
        "(R) TENNESSEE"
      ]
    }
  },
  {
    "at": "00:50:45.142",
    "scene-lebal": "I",
    "scene-subtype-label": "",
    "transitional": false,
    "text-transcript": "JOHN McCORMALLY\n\nHARRIS NEWSPAPERS",
    "keyed-information": {
      "name-as-written": "JOHN McCORMALLY",
      "name-normalized": "McCormally, John",
      "attributes": [
        "HARRIS NEWSPAPERS"
      ]
    }
  },
  {
    "at": "00:52:08.391",
    "scene-lebal": "I",
    "scene-subtype-label": "",
    "transitional": false,
    "text-transcript": "HOWARD BAKER\n\n(R) TENNESSEE",
    "keyed-information": {
      "name-as-written": "HOWARD BAKER",
      "name-normalized": "Baker, Howard",
      "attributes": [
        "(R) TENNESSEE"
      ]
    }
  }
]