[
  {
    "at": "00:02:25.879",
    "scene-lebal": "I",
    "scene-subtype-label": "",
    "transitional": false,
    "text-transcript": "LYNETTE LO TOM\n\nHawaii Edition",
    "keyed-information": {
      "name-as-written": "LYNETTE LO TOM",
      "name-normalized": "Tom, Lynette Lo",
      "attributes": [
        "Hawaii Edition"
      ]
    }
  },
  {
    "at": "00:04:02.008",
    "scene-lebal": "I",
    "scene-subtype-label": "",
    "transitional": false,
    "text-transcript": "JEREMY HARRIS\n\nHonolulu Managing Director",
    "keyed-information": {
      "name-as-written": "JEREMY HARRIS",
      "name-normalized": "Harris, Jeremy",
      "attributes": [
        "Honolulu Managing Director"
      ]
    }
  },
  {
    "at": "00:04:15.255",
    "scene-lebal": "I",
    "scene-subtype-label": "",
    "transitional": false,
    "text-transcript": "Rep. PAUL OSHIRO (D)\n\nTransportation Comm. Chair",
    "keyed-information": {
      "name-as-written": "Rep. PAUL OSHIRO (D)",
      "name-normalized": "Oshiro, Paul",
      "attributes": [
        "Transportation Comm. Chair"
      ]
    }
  },
  {
    "at": "00:05:10.143",
    "scene-lebal": "I",
    "scene-subtype-label": "",
    "transitional": false,
    "text-transcript": "JEREMY HARRIS\n\nHonolulu Managing Director",
    "keyed-information": {
      "name-as-written": "JEREMY HARRIS",
      "name-normalized": "Harris, Jeremy",
      "attributes": [
        "Honolulu Managing Director"
      ]
    }
  },
  {
    "at": "00:05:49.515",
    "scene-lebal": "I",
    "scene-subtype-label": "",
    "transitional": false,
    "text-transcript": "DAVID KAHANU (D)\n\nHonolulu City\n\nCouncil Member",
    "keyed-information": {
      "name-as-written": "DAVID KAHANU (D)",
      "name-normalized": "Kahanu, David",
      "attributes": [
        "Honolulu City Council Member"
      ]
    }
  },
  {
    "at": "00:06:33.259",
    "scene-lebal": "I",
    "scene-subtype-label": "",
    "transitional": false,
    "text-transcript": "DAVID KAHANU (D)\n\nHonolulu City\n\nCouncil Member",
    "keyed-information": {
      "name-as-written": "DAVID KAHANU (D)",
      "name-normalized": "Kahanu, David",
      "attributes": [
        "Honolulu City Council Member"
      ]
    }
  },
  {
    "at": "00:06:47.273",
    "scene-lebal": "I",
    "scene-subtype-label": "",
    "transitional": false,
    "text-transcript": "Rep. PAUL OSHIRO (D)\n\nTransportation Comm. Chair",
    "keyed-information": {
      "name-as-written": "Rep. PAUL OSHIRO (D)",
      "name-normalized": "Oshiro, Paul",
      "attributes": [
        "Transportation Comm. Chair"
      ]
    }
  },
  {
    "at": "00:07:21.641",
    "scene-lebal": "I",
    "scene-subtype-label": "",
    "transitional": false,
    "text-transcript": "Sen. MARY-JANE McMURDO\n\n(D) Waikiki-Moiliili",
    "keyed-information": {
      "name-as-written": "Sen. MARY-JANE McMURDO",
      "name-normalized": "McMurdo, Mary-Jane",
      "attributes": [
        "(D) Waikiki-Moiliili"
      ]
    }
  },
  {
    "at": "00:07:34.887",
    "scene-lebal": "I",
    "scene-subtype-label": "",
    "transitional": false,
    "text-transcript": "KELLY DEAN\n\nHawaii Public Television",
    "keyed-information": {
      "name-as-written": "KELLY DEAN",
      "name-normalized": "Dean, Kelly",
      "attributes": [
        "Hawaii Public Television"
      ]
    }
  },
  {
    "at": "00:10:08.641",
    "scene-lebal": "I",
    "scene-subtype-label": "",
    "transitional": false,
    "text-transcript": "JERRY BURRIS\n\nHonolulu Advertiser",
    "keyed-information": {
      "name-as-written": "JERRY BURRIS",
      "name-normalized": "Burris, Jerry",
      "attributes": [
        "Honolulu Advertiser"
      ]
    }
  },
  {
    "at": "00:10:50.516",
    "scene-lebal": "I",
    "scene-subtype-label": "",
    "transitional": false,
    "text-transcript": "RICHARD BORRECA\n\nHonolulu Star-Bulletin",
    "keyed-information": {
      "name-as-written": "RICHARD BORRECA",
      "name-normalized": "Borreca, Richard",
      "attributes": [
        "Honolulu Star-Bulletin"
      ]
    }
  },
  {
    "at": "00:11:36.262",
    "scene-lebal": "I",
    "scene-subtype-label": "",
    "transitional": false,
    "text-transcript": "BARBARA MARSHALL\n\nTV-2 News",
    "keyed-information": {
      "name-as-written": "BARBARA MARSHALL",
      "name-normalized": "Marshall, Barbara",
      "attributes": [
        "TV-2 News"
      ]
    }
  },
  {
    "at": "00:12:10.396",
    "scene-lebal": "I",
    "scene-subtype-label": "",
    "transitional": false,
    "text-transcript": "GERALD KATO\n\nKGMB News",
    "keyed-information": {
      "name-as-written": "GERALD KATO",
      "name-normalized": "Kato, Gerald",
      "attributes": [
        "KGMB News"
      ]
    }
  },
  {
    "at": "00:13:31.277",
    "scene-lebal": "I",
    "scene-subtype-label": "",
    "transitional": false,
    "text-transcript": "RICHARD BORRECA\n\nHonolulu Star-Bulletin",
    "keyed-information": {
      "name-as-written": "RICHARD BORRECA",
      "name-normalized": "Borreca, Richard",
      "attributes": [
        "Honolulu Star-Bulletin"
      ]
    }
  },
  {
    "at": "00:13:58.504",
    "scene-lebal": "I",
    "scene-subtype-label": "",
    "transitional": false,
    "text-transcript": "JERRY BURRIS\n\nHonolulu Advertiser",
    "keyed-information": {
      "name-as-written": "JERRY BURRIS",
      "name-normalized": "Burris, Jerry",
      "attributes": [
        "Honolulu Advertiser"
      ]
    }
  },
  {
    "at": "00:14:24.763",
    "scene-lebal": "I",
    "scene-subtype-label": "",
    "transitional": false,
    "text-transcript": "GERALD KATO\n\nKGMB News",
    "keyed-information": {
      "name-as-written": "GERALD KATO",
      "name-normalized": "Kato, Gerald",
      "attributes": [
        "KGMB News"
      ]
    }
  },
  {
    "at": "00:18:56.268",
    "scene-lebal": "I",
    "scene-subtype-label": "",
    "transitional": false,
    "text-transcript": "RICHARD BORRECA\n\nHonolulu Star-Bulletin",
    "keyed-information": {
      "name-as-written": "RICHARD BORRECA",
      "name-normalized": "Borreca, Richard",
      "attributes": [
        "Honolulu Star-Bulletin"
      ]
    }
  },
  {
    "at": "00:19:28.000",
    "scene-lebal": "I",
    "scene-subtype-label": "",
    "transitional": false,
    "text-transcript": "JERRY BURRIS\n\nHonolulu Advertiser",
    "keyed-information": {
      "name-as-written": "JERRY BURRIS",
      "name-normalized": "Burris, Jerry",
      "attributes": [
        "Honolulu Advertiser"
      ]
    }
  },
  {
    "at": "00:20:54.253",
    "scene-lebal": "I",
    "scene-subtype-label": "",
    "transitional": false,
    "text-transcript": "GERALD KATO\n\nKGMB News",
    "keyed-information": {
      "name-as-written": "GERALD KATO",
      "name-normalized": "Kato, Gerald",
      "attributes": [
        "KGMB News"
      ]
    }
  },
  {
    "at": "00:23:58.770",
    "scene-lebal": "I",
    "scene-subtype-label": "",
    "transitional": false,
    "text-transcript": "GERALD KATO\n\nKGMB News",
    "keyed-information": {
      "name-as-written": "GERALD KATO",
      "name-normalized": "Kato, Gerald",
      "attributes": [
        "KGMB News"
      ]
    }
  },
  {
    "at": "00:26:13.505",
    "scene-lebal": "I",
    "scene-subtype-label": "",
    "transitional": false,
    "text-transcript": "BARBARA MARSHALL\n\nTV-2 News",
    "keyed-information": {
      "name-as-written": "BARBARA MARSHALL",
      "name-normalized": "Marshall, Barbara",
      "attributes": [
        "TV-2 News"
      ]
    }
  },
  {
    "at": "00:27:52.270",
    "scene-lebal": "I",
    "scene-subtype-label": "",
    "transitional": false,
    "text-transcript": "RICHARD BORRECA\n\nHonolulu Star-Bulletin",
    "keyed-information": {
      "name-as-written": "RICHARD BORRECA",
      "name-normalized": "Borreca, Richard",
      "attributes": [
        "Honolulu Star-Bulletin"
      ]
    }
  }
]