[
  {
    "at": "00:02:29.382",
    "scene-lebal": "I",
    "scene-subtype-label": "",
    "transitional": false,
    "text-transcript": "Roger Morris",
    "keyed-information": {
      "name-as-written": "Roger Morris",
      "name-normalized": "Morris, Roger",
      "attributes": []
    }
  },
  {
    "at": "00:04:50.156",
    "scene-lebal": "I",
    "scene-subtype-label": "",
    "transitional": false,
    "text-transcript": "Estelle Zannes\n\nUNM Associate Professor\n\nDept. Of Communications",
    "keyed-information": {
      "name-as-written": "Estelle Zannes",
      "name-normalized": "Zannes, Estelle",
      "attributes": [
        "UNM Associate Professor Dept. Of Communications"
      ]
    }
  },
  {
    "at": "00:06:30.656",
    "scene-lebal": "I",
    "scene-subtype-label": "",
    "transitional": false,
    "text-transcript": "Dr. F. Chris Garcia\n\nPresident of Zia Reasearch Inc.",
    "keyed-information": {
      "name-as-written": "Dr. F. Chris Garcia",
      "name-normalized": "Garcia, F. Chris",
      "attributes": [
        "President of Zia Reasearch Inc."
      ]
    }
  },
  {
    "at": "00:06:55.014",
    "scene-lebal": "I",
    "scene-subtype-label": "",
    "transitional": false,
    "text-transcript": "Helen Gaussoin\n\nReporter/Sante Fe Reporter",
    "keyed-information": {
      "name-as-written": "Helen Gaussoin",
      "name-normalized": "Reporter/Sante Fe Reporter",
      "attributes": []
    }
  },
  {
    "at": "00:10:31.631",
    "scene-lebal": "I",
    "scene-subtype-label": "",
    "transitional": false,
    "text-transcript": "Dr. F. Chris Garcia\n\nPresident of Zia Research Inc.",
    "keyed-information": {
      "name-as-written": "Dr. F. Chris Garcia",
      "name-normalized": "Garcia, F. Chris",
      "attributes": [
        "President of Zia Research Inc."
      ]
    }
  },
  {
    "at": "00:12:20.773",
    "scene-lebal": "I",
    "scene-subtype-label": "",
    "transitional": false,
    "text-transcript": "Helen Gaussoin \n\nReporter/Sante Fe Reporter",
    "keyed-information": {
      "name-as-written": "Helen Gaussoin",
      "name-normalized": "Gaussoin, Helen",
      "attributes": [
        "Reporter/Sante Fe Reporter"
      ]
    }
  },
  {
    "at": "00:15:23.255",
    "scene-lebal": "I",
    "scene-subtype-label": "",
    "transitional": false,
    "text-transcript": "Helen Gaussoin\n\nReporter/Santa Fe Reporter",
    "keyed-information": {
      "name-as-written": "Helen Gaussoin",
      "name-normalized": "Gaussoin, Helen",
      "attributes": [
        "Reporter/Santa Fe Reporter"
      ]
    }
  },
  {
    "at": "00:16:41.400",
    "scene-lebal": "I",
    "scene-subtype-label": "",
    "transitional": false,
    "text-transcript": "Dr. F. Chris Garcia\n\nPresident of Zia Research Inc.",
    "keyed-information": {
      "name-as-written": "Dr. F. Chris Garcia",
      "name-normalized": "Garcia, F. Chris",
      "attributes": [
        "President of Zia Research Inc."
      ]
    }
  },
  {
    "at": "00:20:16.014",
    "scene-lebal": "I",
    "scene-subtype-label": "",
    "transitional": false,
    "text-transcript": "Helen Gaussoin\n\nReporter/Santa Fe Reporter",
    "keyed-information": {
      "name-as-written": "Helen Gaussoin",
      "name-normalized": "Gaussoin, Helen",
      "attributes": [
        "Reporter/Santa Fe Reporter"
      ]
    }
  },
  {
    "at": "00:22:34.886",
    "scene-lebal": "I",
    "scene-subtype-label": "",
    "transitional": false,
    "text-transcript": "Perry Toles \n\nROSWELL",
    "keyed-information": {
      "name-as-written": "Perry Toles",
      "name-normalized": "Toles, Perry",
      "attributes": [
        "ROSWELL"
      ]
    }
  },
  {
    "at": "00:22:40.625",
    "scene-lebal": "I",
    "scene-subtype-label": "",
    "transitional": false,
    "text-transcript": "Caroline Lopez \n\nLAS VEGAS",
    "keyed-information": {
      "name-as-written": "Caroline Lopez",
      "name-normalized": "Lopez, Caroline",
      "attributes": [
        "LAS VEGAS"
      ]
    }
  },
  {
    "at": "00:22:46.031",
    "scene-lebal": "I",
    "scene-subtype-label": "",
    "transitional": false,
    "text-transcript": "John Pound \n\nSANTA FE",
    "keyed-information": {
      "name-as-written": "John Pound",
      "name-normalized": "Pound, John",
      "attributes": [
        "SANTA FE"
      ]
    }
  },
  {
    "at": "00:23:25.904",
    "scene-lebal": "I",
    "scene-subtype-label": "",
    "transitional": false,
    "text-transcript": "Estelle Zannes\n\nUNM Associate Professor\n\nDept. Of Communications",
    "keyed-information": {
      "name-as-written": "Estelle Zannes",
      "name-normalized": "Zannes, Estelle",
      "attributes": [
        "UNM Associate Professor Dept. Of Communications"
      ]
    }
  },
  {
    "at": "00:24:21.393",
    "scene-lebal": "I",
    "scene-subtype-label": "",
    "transitional": false,
    "text-transcript": "Dr. F. Chris Garcia\n\nPresident of Zia Research Inc.",
    "keyed-information": {
      "name-as-written": "Dr. F. Chris Garcia",
      "name-normalized": "Garcia, F. Chris",
      "attributes": [
        "President of Zia Research Inc."
      ]
    }
  }
]